CHANGELOG.txt
MANIFEST.in
README.txt
setup.py
bot/__init__.py
bot/files/data/response.csv
bot/files/model/model.pk
bot/files/model/vectorizer.pk
bot/src/chat.py
bot/src/predict.py
bot/src/model/models.py
bot/src/utils/constant.py
bot/src/utils/evaluation.py
bot/src/utils/logger.py
bot/src/utils/nlp.py
budibot.egg-info/PKG-INFO
budibot.egg-info/SOURCES.txt
budibot.egg-info/dependency_links.txt
budibot.egg-info/requires.txt
budibot.egg-info/top_level.txt