Metadata-Version: 2.1
Name: budibot
Version: 0.0.1
Summary: NLP Chatbot model for UMKM
Home-page: UNKNOWN
Author: Malvin
Author-email: khoemalvin17@gmail.com
License: MIT
Keywords: Chatbot
Platform: UNKNOWN
Classifier: Development Status :: 5 - Production/Stable
Classifier: Intended Audience :: Education
Classifier: Operating System :: Microsoft :: Windows :: Windows 10
Classifier: License :: OSI Approved :: MIT License
Classifier: Programming Language :: Python :: 3.9
